ntfsutils/__init__.py
ntfsutils/fs.py
ntfsutils/hardlink.py
ntfsutils/junction.py
tests/__init__.py
tests/common.py
tests/test_fs.py
tests/test_hardlink.py
tests/test_junction.py
ntfsutils-0.1.5.dist-info/LICENSE
ntfsutils-0.1.5.dist-info/METADATA
ntfsutils-0.1.5.dist-info/NOTICE.txt
ntfsutils-0.1.5.dist-info/WHEEL
ntfsutils-0.1.5.dist-info/top_level.txt
ntfsutils-0.1.5.dist-info/RECORD
