Metadata-Version: 2.1
Name: ntfsutils
Version: 0.1.5
Summary: A Python module to manipulate NTFS hard links and junctions.
Home-page: https://github.com/sunshowers-code/py-ntfs
Author: Rain
Author-email: rain@sunshowers.io
License: BSD
Keywords: windows ntfs hardlink junction
Platform: UNKNOWN
Classifier: Intended Audience :: Developers
Classifier: Topic :: Software Development :: Libraries :: Python Modules
Classifier: License :: OSI Approved :: BSD License
Classifier: Programming Language :: Python :: 2.7
Classifier: Programming Language :: Python :: 3.2
Classifier: Programming Language :: Python :: 3.3
Classifier: Programming Language :: Python :: 3.4
Classifier: Programming Language :: Python :: 3.5
Classifier: Programming Language :: Python :: 3.6
Classifier: Programming Language :: Python :: 3.7
Classifier: Programming Language :: Python :: 3.8
Classifier: Programming Language :: Python :: 3.9
Classifier: Programming Language :: Python :: 3.10
Classifier: Programming Language :: Python :: 3.11
License-File: LICENSE
License-File: NOTICE.txt
Requires-Dist: setuptools
